radarbox/__init__.py
radarbox/api/__init__.py
radarbox/api/aircraft_api.py
radarbox/api/airports_api.py
radarbox/api/airspace_api.py
radarbox/api/billing_api.py
radarbox/api/flights_api.py
radarbox/api/statistics_api.py
radarbox/api_client.py
radarbox/api_response.py
radarbox/configuration.py
radarbox/exceptions.py
radarbox/models/__init__.py
radarbox/models/airline_statistics_response.py
radarbox/models/airports_statistics_response.py
radarbox/models/api_aircraft.py
radarbox/models/api_aircraft_statistic.py
radarbox/models/api_aircraft_type_utilization.py
radarbox/models/api_aircraft_type_utilization_period.py
radarbox/models/api_airline_statistic.py
radarbox/models/api_airline_statistics.py
radarbox/models/api_airport.py
radarbox/models/api_airport_statistic.py
radarbox/models/api_airport_statistics.py
radarbox/models/api_business_jet_operator_statistic.py
radarbox/models/api_business_jet_operator_statistics.py
radarbox/models/api_coordinates.py
radarbox/models/api_datis.py
radarbox/models/api_flight.py
radarbox/models/api_flight_route_statistic.py
radarbox/models/api_flights_statistic.py
radarbox/models/api_jet_model_statistic.py
radarbox/models/api_jet_model_statistics.py
radarbox/models/api_metar.py
radarbox/models/api_nat_pac_track.py
radarbox/models/api_notam.py
radarbox/models/api_notam_translation.py
radarbox/models/api_runway.py
radarbox/models/api_runway_in_use.py
radarbox/models/api_statistic_airport.py
radarbox/models/api_taf.py
radarbox/models/api_taf_forecast.py
radarbox/models/api_taf_sky_condition.py
radarbox/models/api_track_waypoint.py
radarbox/models/api_trail.py
radarbox/models/billing_status_response.py
radarbox/models/billing_token_daily_stats.py
radarbox/models/billing_usage_response.py
radarbox/models/business_jet_model_statistics_response.py
radarbox/models/business_jet_operator_statistics_response.py
radarbox/models/coordinates.py
radarbox/models/flights_query.py
radarbox/models/flights_response.py
radarbox-1.0.0.dist-info/METADATA
radarbox-1.0.0.dist-info/WHEEL
radarbox-1.0.0.dist-info/RECORD
